<?xml version="1.0" encoding="utf-8" ?><dwsync><file name="views-slideshow-cycle-main-frame-row-item.tpl.php" server="rhswebdev.rhsmith.umd.edu//var/www/it-dev/" local="3480328929" remote="-4611938885441219711" Dst="-1" /><file name="views-slideshow-cycle-main-frame-row.tpl.php" server="rhswebdev.rhsmith.umd.edu//var/www/it-dev/" local="3480328929" remote="-4611938885441219711" Dst="-1" /><file name="views-slideshow-cycle-main-frame.tpl.php" server="rhswebdev.rhsmith.umd.edu//var/www/it-dev/" local="3480328929" remote="-4611938885441219711" Dst="-1" /><file name="views-slideshow-cycle.tpl.php" server="rhswebdev.rhsmith.umd.edu//var/www/it-dev/" local="3480328929" remote="-4611938885441219711" Dst="-1" /><file name="views_slideshow_cycle.theme.inc" server="rhswebdev.rhsmith.umd.edu//var/www/it-dev/" local="3480328929" remote="-4611938885441219711" Dst="-1" /><file name="views_slideshow_cycle.theme.inc" server="it-dev.rhsmith.umd.edu//var/www/it-dev/" local="3480687489" remote="-4611891743880178815" Dst="-1" /><file name="views-slideshow-cycle.tpl.php" server="it-dev.rhsmith.umd.edu//var/www/it-dev/" local="3480687489" remote="-4611891743880178815" Dst="-1" /><file name="views-slideshow-cycle-main-frame-row-item.tpl.php" server="it-dev.rhsmith.umd.edu//var/www/it-dev/" local="3480687489" remote="-4611891743880178815" Dst="-1" /><file name="views-slideshow-cycle-main-frame.tpl.php" server="it-dev.rhsmith.umd.edu//var/www/it-dev/" local="3480687489" remote="-4611891743880178815" Dst="-1" /><file name="views-slideshow-cycle-main-frame-row.tpl.php" server="it-dev.rhsmith.umd.edu//var/www/it-dev/" local="3480687489" remote="-4611891743880178815" Dst="-1" /><file name="views_slideshow_cycle.theme.inc" server="rhswebprod-int.rhsmith.umd.edu//var/www/it/" local="3480687489" remote="7780225742" Dst="-1" /><file name="views-slideshow-cycle.tpl.php" server="rhswebprod-int.rhsmith.umd.edu//var/www/it/" local="3480687489" remote="7780225743" Dst="-1" /><file name="views-slideshow-cycle-main-frame.tpl.php" server="rhswebprod-int.rhsmith.umd.edu//var/www/it/" local="3480687489" remote="7780225743" Dst="-1" /><file name="views-slideshow-cycle-main-frame-row.tpl.php" server="rhswebprod-int.rhsmith.umd.edu//var/www/it/" local="3480687489" remote="7780225743" Dst="-1" /><file name="views-slideshow-cycle-main-frame-row-item.tpl.php" server="rhswebprod-int.rhsmith.umd.edu//var/www/it/" local="3480687489" remote="7780225744" Dst="-1" /></dwsync>