<?xml version="1.0" encoding="utf-8" ?><dwsync><file name="taylor.css" server="it-dev.rhsmith.umd.edu//var/www/it-dev/" local="3484056678" remote="-4611891743876808863" Dst="-1" /><file name="taylor.inc" server="it-dev.rhsmith.umd.edu//var/www/it-dev/" local="3484056678" remote="-4611891743876808863" Dst="-1" /><file name="taylor.png" server="it-dev.rhsmith.umd.edu//var/www/it-dev/" local="3484056678" remote="-4611891743876808862" Dst="-1" /><file name="taylor.tpl.php" server="it-dev.rhsmith.umd.edu//var/www/it-dev/" local="3484056678" remote="-4611891743876808862" Dst="-1" /><file name="taylor.tpl.php" server="rhswebprod-int.rhsmith.umd.edu//var/www/it/" local="3484056678" remote="7780226370" Dst="-1" /><file name="taylor.png" server="rhswebprod-int.rhsmith.umd.edu//var/www/it/" local="3484056678" remote="7780226370" Dst="-1" /><file name="taylor.inc" server="rhswebprod-int.rhsmith.umd.edu//var/www/it/" local="3484056678" remote="7780226371" Dst="-1" /><file name="taylor.css" server="rhswebprod-int.rhsmith.umd.edu//var/www/it/" local="3484056678" remote="7780226371" Dst="-1" /></dwsync>