<?xml version="1.0" encoding="utf-8" ?><dwsync><file name="submit.png" server="rhswebdev.rhsmith.umd.edu//var/www/it-dev/" local="3480936814" remote="-4611823436720047196" Dst="-1" /><file name="loading.gif" server="rhswebdev.rhsmith.umd.edu//var/www/it-dev/" local="3480936814" remote="-4611823436720047196" Dst="-1" /><file name="ops.png" server="rhswebdev.rhsmith.umd.edu//var/www/it-dev/" local="3480936814" remote="-4611823436720047196" Dst="-1" /><file name="tree.png" server="rhswebdev.rhsmith.umd.edu//var/www/it-dev/" local="3480936814" remote="-4611823436720047196" Dst="-1" /><file name="leaf.png" server="rhswebdev.rhsmith.umd.edu//var/www/it-dev/" local="3480936814" remote="-4611823436720047196" Dst="-1" /><file name="op.png" server="rhswebdev.rhsmith.umd.edu//var/www/it-dev/" local="3480936814" remote="-4611823436720047196" Dst="-1" /><file name="upload.png" server="rhswebdev.rhsmith.umd.edu//var/www/it-dev/" local="3480936814" remote="-4611823436720047196" Dst="-1" /><file name="thumb.png" server="rhswebdev.rhsmith.umd.edu//var/www/it-dev/" local="3480936814" remote="-4611823436720047196" Dst="-1" /><file name="resize.png" server="rhswebdev.rhsmith.umd.edu//var/www/it-dev/" local="3480936814" remote="-4611823436720047196" Dst="-1" /><file name="sendto.png" server="rhswebdev.rhsmith.umd.edu//var/www/it-dev/" local="3480936814" remote="-4611823436720047196" Dst="-1" /><file name="view-box.png" server="rhswebdev.rhsmith.umd.edu//var/www/it-dev/" local="3480936814" remote="-4611823436720047196" Dst="-1" /><file name="view-list.png" server="rhswebdev.rhsmith.umd.edu//var/www/it-dev/" local="3480936814" remote="-4611823436720047196" Dst="-1" /><file name="y-resizer.png" server="rhswebdev.rhsmith.umd.edu//var/www/it-dev/" local="3480936814" remote="-4611823436720047196" Dst="-1" /><file name="x-resizer.png" server="rhswebdev.rhsmith.umd.edu//var/www/it-dev/" local="3480936814" remote="-4611823436720047196" Dst="-1" /><file name="status.png" server="rhswebdev.rhsmith.umd.edu//var/www/it-dev/" local="3480936814" remote="-4611823436720047196" Dst="-1" /><file name="warning.png" server="rhswebdev.rhsmith.umd.edu//var/www/it-dev/" local="3480936814" remote="-4611823436720047196" Dst="-1" /><file name="close.png" server="rhswebdev.rhsmith.umd.edu//var/www/it-dev/" local="3480936814" remote="-4611823436720047196" Dst="-1" /><file name="collapsed.png" server="rhswebdev.rhsmith.umd.edu//var/www/it-dev/" local="3480936814" remote="-4611823436720047196" Dst="-1" /><file name="delete.png" server="rhswebdev.rhsmith.umd.edu//var/www/it-dev/" local="3480936814" remote="-4611823436720047196" Dst="-1" /><file name="error.png" server="rhswebdev.rhsmith.umd.edu//var/www/it-dev/" local="3480936814" remote="-4611823436720047196" Dst="-1" /><file name="expanded.png" server="rhswebdev.rhsmith.umd.edu//var/www/it-dev/" local="3480936814" remote="-4611823436720047196" Dst="-1" /><file name="folder-open.png" server="rhswebdev.rhsmith.umd.edu//var/www/it-dev/" local="3480936814" remote="-4611823436720047196" Dst="-1" /><file name="folder-root.png" server="rhswebdev.rhsmith.umd.edu//var/www/it-dev/" local="3480936814" remote="-4611823436720047196" Dst="-1" /><file name="folder.png" server="rhswebdev.rhsmith.umd.edu//var/www/it-dev/" local="3480936814" remote="-4611823436720047196" Dst="-1" /><file name="header.png" server="rhswebdev.rhsmith.umd.edu//var/www/it-dev/" local="3480936814" remote="-4611823436720047196" Dst="-1" /><file name="help.png" server="rhswebdev.rhsmith.umd.edu//var/www/it-dev/" local="3480936814" remote="-4611823436720047196" Dst="-1" /><file name="imce-content.css" server="rhswebdev.rhsmith.umd.edu//var/www/it-dev/" local="3480936814" remote="-4611823436720047196" Dst="-1" /><file name="warning.png" server="it-dev.rhsmith.umd.edu//var/www/it-dev/" local="3480943524" remote="-4611845564391556188" Dst="-1" /><file name="delete.png" server="it-dev.rhsmith.umd.edu//var/www/it-dev/" local="3480943524" remote="-4611845564391556188" Dst="-1" /><file name="op.png" server="it-dev.rhsmith.umd.edu//var/www/it-dev/" local="3480943524" remote="-4611845564391556188" Dst="-1" /><file name="view-list.png" server="it-dev.rhsmith.umd.edu//var/www/it-dev/" local="3480943524" remote="-4611845564391556188" Dst="-1" /><file name="sendto.png" server="it-dev.rhsmith.umd.edu//var/www/it-dev/" local="3480943524" remote="-4611845564391556188" Dst="-1" /><file name="tree.png" server="it-dev.rhsmith.umd.edu//var/www/it-dev/" local="3480943524" remote="-4611845564391556188" Dst="-1" /><file name="ops.png" server="it-dev.rhsmith.umd.edu//var/www/it-dev/" local="3480943524" remote="-4611845564391556188" Dst="-1" /><file name="x-resizer.png" server="it-dev.rhsmith.umd.edu//var/www/it-dev/" local="3480943524" remote="-4611845564391556188" Dst="-1" /><file name="folder-root.png" server="it-dev.rhsmith.umd.edu//var/www/it-dev/" local="3480943524" remote="-4611845564391556188" Dst="-1" /><file name="upload.png" server="it-dev.rhsmith.umd.edu//var/www/it-dev/" local="3480943524" remote="-4611845564391556188" Dst="-1" /><file name="view-box.png" server="it-dev.rhsmith.umd.edu//var/www/it-dev/" local="3480943524" remote="-4611845564391556188" Dst="-1" /><file name="resize.png" server="it-dev.rhsmith.umd.edu//var/www/it-dev/" local="3480943524" remote="-4611845564391556188" Dst="-1" /><file name="folder.png" server="it-dev.rhsmith.umd.edu//var/www/it-dev/" local="3480943524" remote="-4611845564391556188" Dst="-1" /><file name="status.png" server="it-dev.rhsmith.umd.edu//var/www/it-dev/" local="3480943524" remote="-4611845564391556188" Dst="-1" /><file name="submit.png" server="it-dev.rhsmith.umd.edu//var/www/it-dev/" local="3480943524" remote="-4611845564391556188" Dst="-1" /><file name="imce-content.css" server="it-dev.rhsmith.umd.edu//var/www/it-dev/" local="3480943524" remote="-4611845564391556188" Dst="-1" /><file name="leaf.png" server="it-dev.rhsmith.umd.edu//var/www/it-dev/" local="3480943524" remote="-4611845564391556188" Dst="-1" /><file name="loading.gif" server="it-dev.rhsmith.umd.edu//var/www/it-dev/" local="3480943524" remote="-4611845564391556188" Dst="-1" /><file name="folder-open.png" server="it-dev.rhsmith.umd.edu//var/www/it-dev/" local="3480943524" remote="-4611845564391556188" Dst="-1" /><file name="help.png" server="it-dev.rhsmith.umd.edu//var/www/it-dev/" local="3480943524" remote="-4611845564391556188" Dst="-1" /><file name="collapsed.png" server="it-dev.rhsmith.umd.edu//var/www/it-dev/" local="3480943524" remote="-4611845564391556188" Dst="-1" /><file name="close.png" server="it-dev.rhsmith.umd.edu//var/www/it-dev/" local="3480943524" remote="-4611845564391556188" Dst="-1" /><file name="error.png" server="it-dev.rhsmith.umd.edu//var/www/it-dev/" local="3480943524" remote="-4611845564391556188" Dst="-1" /><file name="expanded.png" server="it-dev.rhsmith.umd.edu//var/www/it-dev/" local="3480943524" remote="-4611845564391556188" Dst="-1" /><file name="header.png" server="it-dev.rhsmith.umd.edu//var/www/it-dev/" local="3480943524" remote="-4611845564391556188" Dst="-1" /><file name="y-resizer.png" server="it-dev.rhsmith.umd.edu//var/www/it-dev/" local="3480943524" remote="-4611845564391556188" Dst="-1" /><file name="thumb.png" server="it-dev.rhsmith.umd.edu//var/www/it-dev/" local="3480943524" remote="-4611845564391556188" Dst="-1" /><file name="y-resizer.png" server="rhswebprod-int.rhsmith.umd.edu//var/www/it/" local="3480943524" remote="7780227140" Dst="-1" /><file name="x-resizer.png" server="rhswebprod-int.rhsmith.umd.edu//var/www/it/" local="3480943524" remote="7780227141" Dst="-1" /><file name="warning.png" server="rhswebprod-int.rhsmith.umd.edu//var/www/it/" local="3480943524" remote="7780227142" Dst="-1" /><file name="view-list.png" server="rhswebprod-int.rhsmith.umd.edu//var/www/it/" local="3480943524" remote="7780227142" Dst="-1" /><file name="view-box.png" server="rhswebprod-int.rhsmith.umd.edu//var/www/it/" local="3480943524" remote="7780227149" Dst="-1" /><file name="upload.png" server="rhswebprod-int.rhsmith.umd.edu//var/www/it/" local="3480943524" remote="7780227149" Dst="-1" /><file name="tree.png" server="rhswebprod-int.rhsmith.umd.edu//var/www/it/" local="3480943524" remote="7780227150" Dst="-1" /><file name="thumb.png" server="rhswebprod-int.rhsmith.umd.edu//var/www/it/" local="3480943524" remote="7780227150" Dst="-1" /><file name="submit.png" server="rhswebprod-int.rhsmith.umd.edu//var/www/it/" local="3480943524" remote="7780227150" Dst="-1" /><file name="status.png" server="rhswebprod-int.rhsmith.umd.edu//var/www/it/" local="3480943524" remote="7780227151" Dst="-1" /><file name="sendto.png" server="rhswebprod-int.rhsmith.umd.edu//var/www/it/" local="3480943524" remote="7780227151" Dst="-1" /><file name="resize.png" server="rhswebprod-int.rhsmith.umd.edu//var/www/it/" local="3480943524" remote="7780227152" Dst="-1" /><file name="ops.png" server="rhswebprod-int.rhsmith.umd.edu//var/www/it/" local="3480943524" remote="7780227153" Dst="-1" /><file name="op.png" server="rhswebprod-int.rhsmith.umd.edu//var/www/it/" local="3480943524" remote="7780227153" Dst="-1" /><file name="loading.gif" server="rhswebprod-int.rhsmith.umd.edu//var/www/it/" local="3480943524" remote="7780227154" Dst="-1" /><file name="leaf.png" server="rhswebprod-int.rhsmith.umd.edu//var/www/it/" local="3480943524" remote="7780227154" Dst="-1" /><file name="imce-content.css" server="rhswebprod-int.rhsmith.umd.edu//var/www/it/" local="3480943524" remote="7780227155" Dst="-1" /><file name="help.png" server="rhswebprod-int.rhsmith.umd.edu//var/www/it/" local="3480943524" remote="7780227155" Dst="-1" /><file name="header.png" server="rhswebprod-int.rhsmith.umd.edu//var/www/it/" local="3480943524" remote="7780227155" Dst="-1" /><file name="folder.png" server="rhswebprod-int.rhsmith.umd.edu//var/www/it/" local="3480943524" remote="7780227156" Dst="-1" /><file name="folder-root.png" server="rhswebprod-int.rhsmith.umd.edu//var/www/it/" local="3480943524" remote="7780227156" Dst="-1" /><file name="folder-open.png" server="rhswebprod-int.rhsmith.umd.edu//var/www/it/" local="3480943524" remote="7780227157" Dst="-1" /><file name="expanded.png" server="rhswebprod-int.rhsmith.umd.edu//var/www/it/" local="3480943524" remote="7780227157" Dst="-1" /><file name="error.png" server="rhswebprod-int.rhsmith.umd.edu//var/www/it/" local="3480943524" remote="7780227157" Dst="-1" /><file name="delete.png" server="rhswebprod-int.rhsmith.umd.edu//var/www/it/" local="3480943524" remote="7780227158" Dst="-1" /><file name="collapsed.png" server="rhswebprod-int.rhsmith.umd.edu//var/www/it/" local="3480943524" remote="7780227158" Dst="-1" /><file name="close.png" server="rhswebprod-int.rhsmith.umd.edu//var/www/it/" local="3480943524" remote="7780227158" Dst="-1" /></dwsync>