<?xml version="1.0" encoding="utf-8" ?><dwsync><file name="Access-Plugins--Determining-access-and-visib" server="rhswebdev.rhsmith.umd.edu//var/www/it-dev/" local="3480328929" remote="-4611915795697036492" Dst="-1" /><file name="Argument-Plugins--Starting-at-the-beginning." server="rhswebdev.rhsmith.umd.edu//var/www/it-dev/" local="3480328929" remote="-4611915795697036492" Dst="-1" /><file name="Chaos-Tools--CTools--Plugin-Examples.html" server="rhswebdev.rhsmith.umd.edu//var/www/it-dev/" local="3480328929" remote="-4611915795697036492" Dst="-1" /><file name="Content-Type-Plugins--Displaying-content-usi" server="rhswebdev.rhsmith.umd.edu//var/www/it-dev/" local="3480328929" remote="-4611915795697036492" Dst="-1" /><file name="Context-plugins--Creating-a--context--from-a" server="rhswebdev.rhsmith.umd.edu//var/www/it-dev/" local="3480328929" remote="-4611915795697036492" Dst="-1" /><file name="ctools_plugin_example.help.ini" server="rhswebdev.rhsmith.umd.edu//var/www/it-dev/" local="3480328929" remote="-4611915795697036492" Dst="-1" /><file name="Module-setup-and-hooks.html" server="rhswebdev.rhsmith.umd.edu//var/www/it-dev/" local="3480328929" remote="-4611915795697036492" Dst="-1" /><file name="Relationships--Letting-one-context-take-us-t" server="rhswebdev.rhsmith.umd.edu//var/www/it-dev/" local="3480328929" remote="-4611915795697036492" Dst="-1" /><file name="Argument-Plugins--Starting-at-the-beginning." server="it-dev.rhsmith.umd.edu//var/www/it-dev/" local="3480687412" remote="-4611868654135995596" Dst="-1" /><file name="Relationships--Letting-one-context-take-us-t" server="it-dev.rhsmith.umd.edu//var/www/it-dev/" local="3480687412" remote="-4611868654135995596" Dst="-1" /><file name="Chaos-Tools--CTools--Plugin-Examples.html" server="it-dev.rhsmith.umd.edu//var/www/it-dev/" local="3480687412" remote="-4611868654135995596" Dst="-1" /><file name="Content-Type-Plugins--Displaying-content-usi" server="it-dev.rhsmith.umd.edu//var/www/it-dev/" local="3480687412" remote="-4611868654135995596" Dst="-1" /><file name="Context-plugins--Creating-a--context--from-a" server="it-dev.rhsmith.umd.edu//var/www/it-dev/" local="3480687412" remote="-4611868654135995596" Dst="-1" /><file name="ctools_plugin_example.help.ini" server="it-dev.rhsmith.umd.edu//var/www/it-dev/" local="3480687412" remote="-4611868654135995596" Dst="-1" /><file name="Access-Plugins--Determining-access-and-visib" server="it-dev.rhsmith.umd.edu//var/www/it-dev/" local="3480687412" remote="-4611868654135995596" Dst="-1" /><file name="Module-setup-and-hooks.html" server="it-dev.rhsmith.umd.edu//var/www/it-dev/" local="3480687412" remote="-4611868654135995596" Dst="-1" /><file name="Relationships--Letting-one-context-take-us-t" server="rhswebprod-int.rhsmith.umd.edu//var/www/it/" local="3480687412" remote="7780227674" Dst="-1" /><file name="Module-setup-and-hooks.html" server="rhswebprod-int.rhsmith.umd.edu//var/www/it/" local="3480687412" remote="7780227674" Dst="-1" /><file name="ctools_plugin_example.help.ini" server="rhswebprod-int.rhsmith.umd.edu//var/www/it/" local="3480687412" remote="7780227675" Dst="-1" /><file name="Context-plugins--Creating-a--context--from-a" server="rhswebprod-int.rhsmith.umd.edu//var/www/it/" local="3480687412" remote="7780227675" Dst="-1" /><file name="Content-Type-Plugins--Displaying-content-usi" server="rhswebprod-int.rhsmith.umd.edu//var/www/it/" local="3480687412" remote="7780227675" Dst="-1" /><file name="Chaos-Tools--CTools--Plugin-Examples.html" server="rhswebprod-int.rhsmith.umd.edu//var/www/it/" local="3480687412" remote="7780227676" Dst="-1" /><file name="Argument-Plugins--Starting-at-the-beginning." server="rhswebprod-int.rhsmith.umd.edu//var/www/it/" local="3480687412" remote="7780227676" Dst="-1" /><file name="Access-Plugins--Determining-access-and-visib" server="rhswebprod-int.rhsmith.umd.edu//var/www/it/" local="3480687412" remote="7780227676" Dst="-1" /></dwsync>