<?xml version="1.0" encoding="utf-8" ?><dwsync><file name="flexslider-views-slideshow-main-frame-row-item.tpl.php" server="rhswebdev.rhsmith.umd.edu//var/www/it-dev/" local="3480334664" remote="-4611892705952853171" Dst="-1" /><file name="flexslider-views-slideshow-main-frame-row.tpl.php" server="rhswebdev.rhsmith.umd.edu//var/www/it-dev/" local="3480334664" remote="-4611892705952853171" Dst="-1" /><file name="flexslider-views-slideshow-main-frame.tpl.php" server="rhswebdev.rhsmith.umd.edu//var/www/it-dev/" local="3480334664" remote="-4611892705952853171" Dst="-1" /><file name="flexslider-views-slideshow.tpl.php" server="rhswebdev.rhsmith.umd.edu//var/www/it-dev/" local="3480334664" remote="-4611892705952853171" Dst="-1" /><file name="flexslider_views_slideshow.theme.inc" server="rhswebdev.rhsmith.umd.edu//var/www/it-dev/" local="3480334664" remote="-4611892705952853171" Dst="-1" /><file name="flexslider-views-slideshow-main-frame.tpl.php" server="it-dev.rhsmith.umd.edu//var/www/it-dev/" local="3480687437" remote="-4611845564391812275" Dst="-1" /><file name="flexslider_views_slideshow.theme.inc" server="it-dev.rhsmith.umd.edu//var/www/it-dev/" local="3480687437" remote="-4611845564391812275" Dst="-1" /><file name="flexslider-views-slideshow-main-frame-row-item.tpl.php" server="it-dev.rhsmith.umd.edu//var/www/it-dev/" local="3480687437" remote="-4611845564391812275" Dst="-1" /><file name="flexslider-views-slideshow-main-frame-row.tpl.php" server="it-dev.rhsmith.umd.edu//var/www/it-dev/" local="3480687437" remote="-4611845564391812275" Dst="-1" /><file name="flexslider-views-slideshow.tpl.php" server="it-dev.rhsmith.umd.edu//var/www/it-dev/" local="3480687437" remote="-4611845564391812275" Dst="-1" /><file name="flexslider_views_slideshow.theme.inc" server="rhswebprod-int.rhsmith.umd.edu//var/www/it/" local="3480687437" remote="7780227233" Dst="-1" /><file name="flexslider-views-slideshow.tpl.php" server="rhswebprod-int.rhsmith.umd.edu//var/www/it/" local="3480687437" remote="7780227233" Dst="-1" /><file name="flexslider-views-slideshow-main-frame.tpl.php" server="rhswebprod-int.rhsmith.umd.edu//var/www/it/" local="3480687437" remote="7780227234" Dst="-1" /><file name="flexslider-views-slideshow-main-frame-row.tpl.php" server="rhswebprod-int.rhsmith.umd.edu//var/www/it/" local="3480687437" remote="7780227234" Dst="-1" /><file name="flexslider-views-slideshow-main-frame-row-item.tpl.php" server="rhswebprod-int.rhsmith.umd.edu//var/www/it/" local="3480687437" remote="7780227234" Dst="-1" /></dwsync>