<?xml version="1.0" encoding="utf-8" ?><dwsync><file name="views_handler_argument_file_fid.inc" server="it-dev.rhsmith.umd.edu//var/www/it-dev/" local="3484056678" remote="-4611868654132625447" Dst="-1" /><file name="views_handler_field_file.inc" server="it-dev.rhsmith.umd.edu//var/www/it-dev/" local="3484056678" remote="-4611868654132625447" Dst="-1" /><file name="views_handler_field_file_extension.inc" server="it-dev.rhsmith.umd.edu//var/www/it-dev/" local="3484056678" remote="-4611868654132625447" Dst="-1" /><file name="views_handler_field_file_filemime.inc" server="it-dev.rhsmith.umd.edu//var/www/it-dev/" local="3484056678" remote="-4611868654132625447" Dst="-1" /><file name="views_handler_field_file_status.inc" server="it-dev.rhsmith.umd.edu//var/www/it-dev/" local="3484056678" remote="-4611868654132625446" Dst="-1" /><file name="views_handler_field_file_uri.inc" server="it-dev.rhsmith.umd.edu//var/www/it-dev/" local="3484056678" remote="-4611868654132625446" Dst="-1" /><file name="views_handler_filter_file_status.inc" server="it-dev.rhsmith.umd.edu//var/www/it-dev/" local="3484056678" remote="-4611868654132625446" Dst="-1" /><file name="views_handler_filter_system_type.inc" server="it-dev.rhsmith.umd.edu//var/www/it-dev/" local="3484056678" remote="-4611868654132625446" Dst="-1" /><file name="views_handler_filter_system_type.inc" server="rhswebprod-int.rhsmith.umd.edu//var/www/it/" local="3484056678" remote="7780225920" Dst="-1" /><file name="views_handler_filter_file_status.inc" server="rhswebprod-int.rhsmith.umd.edu//var/www/it/" local="3484056678" remote="7780225921" Dst="-1" /><file name="views_handler_field_file_uri.inc" server="rhswebprod-int.rhsmith.umd.edu//var/www/it/" local="3484056678" remote="7780225922" Dst="-1" /><file name="views_handler_field_file_status.inc" server="rhswebprod-int.rhsmith.umd.edu//var/www/it/" local="3484056678" remote="7780225923" Dst="-1" /><file name="views_handler_field_file_filemime.inc" server="rhswebprod-int.rhsmith.umd.edu//var/www/it/" local="3484056678" remote="7780225923" Dst="-1" /><file name="views_handler_field_file_extension.inc" server="rhswebprod-int.rhsmith.umd.edu//var/www/it/" local="3484056678" remote="7780225924" Dst="-1" /><file name="views_handler_field_file.inc" server="rhswebprod-int.rhsmith.umd.edu//var/www/it/" local="3484056678" remote="7780225924" Dst="-1" /><file name="views_handler_argument_file_fid.inc" server="rhswebprod-int.rhsmith.umd.edu//var/www/it/" local="3484056678" remote="7780225924" Dst="-1" /></dwsync>